{
  "consentId": "consent_1767177085499_c6e6da937bf44a52",
  "timestamp": "2025-12-31T10:31:31.247Z",
  "consent": {
    "operation": {
      "type": "layout_modification",
      "description": "Ajouter le champ secteur aux layouts Lead",
      "details": {
        "entity": "Lead",
        "fieldName": "secteur",
        "layoutTypes": [
          "detail",
          "list"
        ]
      },
      "tenantId": "macrea-admin"
    },
    "createdAt": "2025-12-31T10:31:25.499Z",
    "usedAt": "2025-12-31T10:31:30.434Z",
    "duration": 4935
  },
  "result": {
    "operation": {
      "type": "layout_modification",
      "description": "Ajouter le champ secteur aux layouts Lead",
      "details": {
        "entity": "Lead",
        "fieldName": "secteur",
        "layoutTypes": [
          "detail",
          "list"
        ]
      },
      "tenantId": "macrea-admin"
    },
    "result": {
      "success": true,
      "entity": "Lead",
      "fieldName": "secteur",
      "layoutsModified": 2,
      "layoutsSkipped": 0,
      "results": [
        {
          "layoutType": "detail",
          "status": "added"
        },
        {
          "layoutType": "list",
          "status": "added"
        }
      ],
      "timestamp": "2025-12-31 10:31:31"
    },
    "executedAt": "2025-12-31T10:31:31.247Z"
  },
  "metadata": {
    "nodeVersion": "v22.14.0",
    "platform": "win32",
    "pid": 25324
  }
}